a/__init__.py
a/module.py
b/__init__.py
b/module.py
nc12-2.2.2.dist-info/METADATA
nc12-2.2.2.dist-info/WHEEL
nc12-2.2.2.dist-info/top_level.txt
nc12-2.2.2.dist-info/RECORD
