Metadata-Version: 2.1
Name: nc12
Version: 2.2.2
Summary: NC12_01
Author: luyendd
Author-email: tudu8603@gmail.com
